spi/src/spi_slave.v
module spi_slave (
    input clk,
    input reset,
    output [7:0] rx_data,
    input [7:0] tx_data,

    //spi
    input spi_clk,
    output miso,
    input mosi,
    input cs,
    output rx_done,
    output tx_done
);

reg rx_done_r, tx_done_r, miso_r, autoreset;
reg[3:0] cont, cont_tx, cont_sclk;
reg [7:0]rx_data_r, tx_data_r;

assign rx_done = rx_done_r;
assign tx_done = tx_done_r;
assign miso = miso_r;

initial begin
    cont = 0;
    rx_data_r = 8'b0;
    rx_done_r = 1'b1;
    tx_done_r = 1'b1;
    miso_r = 0;
    cont_tx = 0;
    tx_data_r = 0;
    cont_sclk = 0;
    autoreset = 0;
end

always @(posedge spi_clk ) begin
    if(~reset) begin // isso e uma gambiarra por causa do sintetizador
        cont <= 0;
        rx_data_r <= 8'b0;
    end else if(~cs) begin
        if(cont == 0)begin
            rx_done_r <= 0;
            rx_data_r <= {rx_data_r[6:0], mosi};
            cont <= cont + 1;
        end else if(cont < 8) begin 
            rx_data_r <= {rx_data_r[6:0], mosi};
            cont <= cont + 1;
            if(cont == 7) begin
                rx_done_r <= 1;
            end
        end else begin
            cont <= 0;
        end
    end
end

always @(negedge spi_clk ) begin
    if(cont == 8) begin 
        cont_sclk <= 0;
    end
    else begin
        cont_sclk = cont_sclk + 1;
    end
end


always @(posedge clk ) begin
    if(~reset) begin // isso e uma gambiarra por causa do sintetizador
        cont_tx <= 0;
        miso_r <= 0;
    end else if(~cs) begin
        if(cont_tx == 0) begin // isso de certa forma faz um autoreset, não sei  se e legal, mas achei util
            tx_data_r = tx_data;
            tx_done_r <= 0;
        end
        if(cont_tx < 8) begin //semaphore
            miso_r <= tx_data_r[7];
            if(cont_tx < cont_sclk ) begin
                tx_data_r <= {tx_data_r[6:0], 1'b0};
                cont_tx <= cont_tx + 1;
            end
        end else begin
            tx_done_r <= 1;
            cont_tx <= 0;
            miso_r <= 0;
        end
    end else begin
        miso_r <= 0;
        tx_done_r <= 1;
        if(cont_sclk == 0) begin
            cont_tx <= 0;
        end
    end
end

assign rx_data = rx_data_r;
    
endmodule
// pra implementar divisão de clock, precisa organizar envio de acordo com spiclk

spi/src/spi_master.v
module spi_master (
    input clk,
    input reset,
    output spi_clk, // clk da spi
    output mosi, // master output slave input
    input miso, // master input slave output
    output cs, // chip select
    input [7:0] tx_data, 
    output [7:0] rx_data,
    output tx_done,  // Sinal indicando que a transmissão está concluída
    output rx_done
);

parameter START = 0, WORK = 1, STOP = 2;
parameter CLK_DIV = 270;

reg mosi_r, cs_r, tx_done_r, rx_done_r, clk_r, trig;
reg [1:0] state = STOP; // estados da maquina
reg [3:0] cont = 0, cont_rx = 0;
reg [7:0] tx_data_r, rx_data_r;

reg [9:0]clk_counter = 0;

assign spi_clk = clk_r;
assign mosi = mosi_r;
assign cs = cs_r;
assign tx_done = tx_done_r;
assign rx_data = rx_data_r;
assign rx_done = rx_done_r;

initial begin
    cs_r = 1;
    tx_done_r = 1;
    rx_done_r = 1;
    mosi_r = 0;
    clk_r = 0;
    clk_counter = 0;
end

always @(posedge clk) begin
    if (~reset) begin
        state <= START;
        mosi_r <= 1'b0;
        tx_done_r <= 1'b0;
        cs_r <= 1'b1;
        tx_data_r <= tx_data;
        clk_r <= 0;
    end else begin
        case (state)
            START: begin
                cs_r <= 1'b0;
                state <= WORK;
                trig <= 1'b1;
                cont <= 0;
                clk_counter <= 0;
            end
            WORK: begin
                if(clk_counter == 0) begin
                    tx_data_r <= {tx_data_r[6:0], 1'b0};
                    mosi_r <= tx_data_r[7];
                    cont <= cont + 1;
                    clk_r <= 1'b0; // eu inverti, para subida do clock, bater com o meio do sinal antes tava 1
                    clk_counter <= clk_counter + 1;
                end else if(clk_counter == CLK_DIV /2) begin 
                    clk_r <= 1'b1;
                    clk_counter <= clk_counter + 1;
                end else begin
                    clk_counter <= clk_counter + 1;
                end

                if(clk_counter == CLK_DIV - 1) begin
                    if(cont == 8)
                        state <= STOP; 
                    clk_counter <= 0;
                end
            end
            STOP: begin
                if(trig) begin // faz o cs subir um ciclo de clock depois
                    trig = 0;
                end else begin
                    cs_r <= 1'b1;
                end
                tx_done_r <= 1'b1;
                state <= STOP;
                mosi_r <= 1'b0;
                clk_r = 0;
            end
            default: begin
                state <= STOP;
            end
        endcase // case
    end // reset
end // always

always @(posedge spi_clk ) begin
    if (~reset) begin
        cont_rx <= 0;
    end else if(~cs) begin
        if(cont_rx == 0)begin
            rx_done_r <= 0;
            rx_data_r <= {rx_data_r[6:0], miso};
            cont_rx <= cont_rx + 1;
        end else if(cont_rx < 8) begin 
            rx_data_r <= {rx_data_r[6:0], miso};
            cont_rx <= cont_rx + 1;
            if(cont_rx == 7)
                rx_done_r <= 1;
        end else begin
            cont_rx <= 0;
        end
    end   // cs
end // always
    
endmodule

spi/src/spi_test.v
module test();

always #1 clk=~clk;

reg clk, reset = 1, reset_slave = 1;

wire mosi, sclk, cs, tx_d, rx_d, miso, slave_d, slave_tx_d;

reg [7:0] data = 8'b10110111, data_slave = 8'b10101101;
wire [7:0] rx_data, rx_master_data;

spi_master u1(
    .clk(clk),
    .reset(reset),
    .spi_clk(sclk),
    .mosi(mosi),
    .miso(miso),
    .cs(cs),
    .tx_done(tx_d),
    .rx_done(rx_d),
    .tx_data(data),
    .rx_data(rx_master_data)
);

spi_slave u2(
    .clk(clk),
    .reset(reset_slave),
    .spi_clk(sclk),
    .mosi(mosi),
    .miso(miso),
    .cs(cs),
    .rx_data(rx_data),
    .rx_done(slave_d),
    .tx_done(slave_tx_d),
    .tx_data(data_slave)
);

initial begin
    clk = 0;
    $dumpfile("spi.vcd");
    $dumpvars;

    $display("RX data %d", rx_data);
    $display("TX slave data %b", data_slave);

    #1
    reset = 0;
    reset_slave = 0;

    #2
    reset = 1;
    reset_slave = 1;

    #200 // a formula e div_clk * 40 

    $display("TX Done %b", slave_tx_d);
    $display("RX Done %b", slave_d);
    $display("RX data %b", rx_data);
    $display("RX data master %b", rx_master_data);

    $display("");

    $display("Segundo round");

    data = 8'b11111011;
    data_slave = 8'b10001001;

    $display("TX master %b", data);
    $display("TX slave data %b", data_slave);

    $display("");

    $display("RX master %b", rx_master_data);
    $display("RX slave data %b", rx_data);

    $display("");

    #2

    //reset_slave = 0;
    reset = 0;

    #2

    reset = 1;
    //reset_slave = 1;

    #200 // a formula e div_clk * 40 

    $display("TX master %b", data);
    $display("TX slave data %b", data_slave);

    $display("");

    $display("RX master %b", rx_master_data);
    $display("RX slave data %b", rx_data);

    $finish;

end

endmodule

spi/spi.vcd
$date
	Wed Nov  8 11:05:25 2023
$end
$version
	Icarus Verilog
$end
$timescale
	1s
$end
$scope module test $end
$var wire 1 ! tx_d $end
$var wire 1 " slave_tx_d $end
$var wire 1 # slave_d $end
$var wire 1 $ sclk $end
$var wire 8 % rx_master_data [7:0] $end
$var wire 8 & rx_data [7:0] $end
$var wire 1 ' rx_d $end
$var wire 1 ( mosi $end
$var wire 1 ) miso $end
$var wire 1 * cs $end
$var reg 1 + clk $end
$var reg 8 , data [7:0] $end
$var reg 8 - data_slave [7:0] $end
$var reg 1 . reset $end
$var reg 1 / reset_slave $end
$scope module u1 $end
$var wire 1 + clk $end
$var wire 1 * cs $end
$var wire 1 ( mosi $end
$var wire 1 . reset $end
$var wire 8 0 rx_data [7:0] $end
$var wire 1 ' rx_done $end
$var wire 1 $ spi_clk $end
$var wire 8 1 tx_data [7:0] $end
$var wire 1 ! tx_done $end
$var wire 1 ) miso $end
$var parameter 32 2 CLK_DIV $end
$var parameter 32 3 START $end
$var parameter 32 4 STOP $end
$var parameter 32 5 WORK $end
$var reg 10 6 clk_counter [9:0] $end
$var reg 1 7 clk_r $end
$var reg 4 8 cont [3:0] $end
$var reg 4 9 cont_rx [3:0] $end
$var reg 1 : cs_r $end
$var reg 1 ; mosi_r $end
$var reg 8 < rx_data_r [7:0] $end
$var reg 1 = rx_done_r $end
$var reg 2 > state [1:0] $end
$var reg 1 ? trig $end
$var reg 8 @ tx_data_r [7:0] $end
$var reg 1 A tx_done_r $end
$upscope $end
$scope module u2 $end
$var wire 1 + clk $end
$var wire 1 * cs $end
$var wire 1 ) miso $end
$var wire 1 ( mosi $end
$var wire 1 / reset $end
$var wire 8 B rx_data [7:0] $end
$var wire 1 # rx_done $end
$var wire 1 $ spi_clk $end
$var wire 8 C tx_data [7:0] $end
$var wire 1 " tx_done $end
$var reg 1 D autoreset $end
$var reg 4 E cont [3:0] $end
$var reg 4 F cont_sclk [3:0] $end
$var reg 4 G cont_tx [3:0] $end
$var reg 1 H miso_r $end
$var reg 8 I rx_data_r [7:0] $end
$var reg 1 J rx_done_r $end
$var reg 8 K tx_data_r [7:0] $end
$var reg 1 L tx_done_r $end
$upscope $end
$upscope $end
$enddefinitions $end
$comment Show the parameter values. $end
$dumpall
b1 5
b10 4
b0 3
b10 2
$end
#0
$dumpvars
1L
b0 K
1J
b0 I
0H
b0 G
b0 F
b0 E
0D
b10101101 C
b0 B
1A
bx @
x?
b10 >
1=
bx <
0;
1:
b0 9
b0 8
07
b0 6
b10110111 1
bx 0
1/
1.
b10101101 -
b10110111 ,
0+
1*
0)
0(
1'
b0 &
bx %
0$
1#
1"
1!
$end
#1
b10110111 @
0!
0A
b0 >
0/
0.
1+
#2
0+
#3
1?
b1 >
0*
0:
1+
1/
1.
#4
0+
#5
b1 6
b1 8
1(
1;
b1101110 @
1)
1H
0"
0L
b10101101 K
1+
#6
0+
#7
b1 9
bx1 %
bx1 0
bx1 <
0'
0=
b1 E
b1 &
b1 B
b1 I
0#
0J
b0 6
1$
17
1+
#8
0+
#9
b1 F
b1 6
0$
07
b10 8
0(
0;
b11011100 @
1+
#10
0+
#11
b10 E
b10 &
b10 B
b10 I
b10 9
bx11 %
bx11 0
bx11 <
b1 G
b1011010 K
b0 6
1$
17
1+
#12
0+
#13
b10 F
b1 6
0$
07
b11 8
1(
1;
b10111000 @
0)
0H
1+
#14
0+
#15
b11 9
bx110 %
bx110 0
bx110 <
b11 E
b101 &
b101 B
b101 I
b10 G
b10110100 K
b0 6
1$
17
1+
#16
0+
#17
b11 F
b1 6
0$
07
b100 8
b1110000 @
1)
1H
1+
#18
0+
#19
b100 E
b1011 &
b1011 B
b1011 I
b100 9
bx1101 %
bx1101 0
bx1101 <
b11 G
b1101000 K
b0 6
1$
17
1+
#20
0+
#21
b100 F
b1 6
0$
07
b101 8
0(
0;
b11100000 @
0)
0H
1+
#22
0+
#23
b101 9
bx11010 %
bx11010 0
bx11010 <
b101 E
b10110 &
b10110 B
b10110 I
b100 G
b11010000 K
b0 6
1$
17
1+
#24
0+
#25
b101 F
b1 6
0$
07
b110 8
1(
1;
b11000000 @
1)
1H
1+
#26
0+
#27
b110 E
b101101 &
b101101 B
b101101 I
b110 9
bx110101 %
bx110101 0
bx110101 <
b101 G
b10100000 K
b0 6
1$
17
1+
#28
0+
#29
b110 F
b1 6
0$
07
b111 8
b10000000 @
1+
#30
0+
#31
b111 9
bx1101011 %
bx1101011 0
bx1101011 <
b111 E
b1011011 &
b1011011 B
b1011011 I
b110 G
b1000000 K
b0 6
1$
17
1+
#32
0+
#33
b111 F
b1 6
0$
07
b1000 8
b0 @
0)
0H
1+
#34
0+
#35
1#
1J
b1000 E
b10110111 &
b10110111 B
b10110111 I
1'
1=
b1000 9
b11010110 %
b11010110 0
b11010110 <
b111 G
b10000000 K
b10 >
b0 6
1$
17
1+
#36
0+
#37
b0 F
0(
0;
1!
1A
1)
1H
0$
07
0?
1+
#38
0+
#39
1*
1:
1+
#40
0+
#41
b0 G
1"
1L
0)
0H
1+
