spi/src/spi_slave.v
module spi_slave (
    input clk,
    input reset,
    output [7:0] rx_data,
    input [7:0] tx_data,

    //spi
    input spi_clk,
    output miso,
    input mosi,
    input cs,
    output rx_done,
    output tx_done
);

reg rx_done_r, tx_done_r, miso_r, autoreset;
reg[3:0] cont, cont_tx, cont_sclk;
reg [7:0]rx_data_r, tx_data_r;

assign rx_done = rx_done_r;
assign tx_done = tx_done_r;
assign miso = miso_r;

initial begin
    cont = 0;
    rx_data_r = 8'b0;
    rx_done_r = 1'b1;
    tx_done_r = 1'b1;
    miso_r = 0;
    cont_tx = 0;
    tx_data_r = 0;
    cont_sclk = 0;
    autoreset = 0;
end

always @(posedge spi_clk ) begin
    if(~reset) begin // isso e uma gambiarra por causa do sintetizador
        cont <= 0;
        rx_data_r <= 8'b0;
    end else if(~cs) begin
        if(cont == 0)begin
            rx_done_r <= 0;
            rx_data_r <= {rx_data_r[6:0], mosi};
            cont <= cont + 1;
        end else if(cont < 8) begin 
            rx_data_r <= {rx_data_r[6:0], mosi};
            cont <= cont + 1;
            if(cont == 7) begin
                rx_done_r <= 1;
            end
        end else begin
            cont <= 0;
        end
    end
end

always @(negedge spi_clk ) begin
    if(cont == 8) begin 
        cont_sclk <= 0;
    end
    else begin
        cont_sclk = cont_sclk + 1;
    end
end


always @(posedge clk ) begin
    if(~reset) begin // isso e uma gambiarra por causa do sintetizador
        cont_tx <= 0;
        miso_r <= 0;
    end else if(~cs) begin
        if(cont_tx == 0) begin // isso de certa forma faz um autoreset, não sei  se e legal, mas achei util
            tx_data_r = tx_data;
            tx_done_r <= 0;
        end
        if(cont_tx < 8) begin //semaphore
            miso_r <= tx_data_r[7];
            if(cont_tx < cont_sclk ) begin
                tx_data_r <= {tx_data_r[6:0], 1'b0};
                cont_tx <= cont_tx + 1;
            end
        end else begin
            tx_done_r <= 1;
            cont_tx <= 0;
            miso_r <= 0;
        end
    end else begin
        miso_r <= 0;
        tx_done_r <= 1;
        if(cont_sclk == 0) begin
            cont_tx <= 0;
        end
    end
end

assign rx_data = rx_data_r;
    
endmodule
// pra implementar divisão de clock, precisa organizar envio de acordo com spiclk

spi/src/spi_master.v
module spi_master (
    input clk,
    input reset,
    output spi_clk, // clk da spi
    output mosi, // master output slave input
    input miso, // master input slave output
    output cs, // chip select
    input [7:0] tx_data, 
    output [7:0] rx_data,
    output tx_done,  // Sinal indicando que a transmissão está concluída
    output rx_done
);

parameter START = 0, WORK = 1, STOP = 2;
parameter CLK_DIV = 270;

reg mosi_r, cs_r, tx_done_r, rx_done_r, clk_r, trig;
reg [1:0] state = STOP; // estados da maquina
reg [3:0] cont = 0, cont_rx = 0;
reg [7:0] tx_data_r, rx_data_r;

reg [9:0]clk_counter = 0;

assign spi_clk = clk_r;
assign mosi = mosi_r;
assign cs = cs_r;
assign tx_done = tx_done_r;
assign rx_data = rx_data_r;
assign rx_done = rx_done_r;

initial begin
    cs_r = 1;
    tx_done_r = 1;
    rx_done_r = 1;
    mosi_r = 0;
    clk_r = 0;
    clk_counter = 0;
end

always @(posedge clk) begin
    if (~reset) begin
        state <= START;
        mosi_r <= 1'b0;
        tx_done_r <= 1'b0;
        cs_r <= 1'b1;
        tx_data_r <= tx_data;
        clk_r <= 0;
    end else begin
        case (state)
            START: begin
                cs_r <= 1'b0;
                state <= WORK;
                trig <= 1'b1;
                cont <= 0;
                clk_counter <= 0;
            end
            WORK: begin
                if(clk_counter == 0) begin
                    tx_data_r <= {tx_data_r[6:0], 1'b0};
                    mosi_r <= tx_data_r[7];
                    cont <= cont + 1;
                    clk_r <= 1'b0; // eu inverti, para subida do clock, bater com o meio do sinal antes tava 1
                    clk_counter <= clk_counter + 1;
                end else if(clk_counter == CLK_DIV /2) begin 
                    clk_r <= 1'b1;
                    clk_counter <= clk_counter + 1;
                end else begin
                    clk_counter <= clk_counter + 1;
                end

                if(clk_counter == CLK_DIV - 1) begin
                    if(cont == 8)
                        state <= STOP; 
                    clk_counter <= 0;
                end
            end
            STOP: begin
                if(trig) begin // faz o cs subir um ciclo de clock depois
                    trig = 0;
                end else begin
                    cs_r <= 1'b1;
                end
                tx_done_r <= 1'b1;
                state <= STOP;
                mosi_r <= 1'b0;
                clk_r = 0;
            end
            default: begin
                state <= STOP;
            end
        endcase // case
    end // reset
end // always

always @(posedge spi_clk ) begin
    if (~reset) begin
        cont_rx <= 0;
    end else if(~cs) begin
        if(cont_rx == 0)begin
            rx_done_r <= 0;
            rx_data_r <= {rx_data_r[6:0], miso};
            cont_rx <= cont_rx + 1;
        end else if(cont_rx < 8) begin 
            rx_data_r <= {rx_data_r[6:0], miso};
            cont_rx <= cont_rx + 1;
            if(cont_rx == 7)
                rx_done_r <= 1;
        end else begin
            cont_rx <= 0;
        end
    end   // cs
end // always
    
endmodule

spi/src/spi_test.v
module test();

always #1 clk=~clk;

reg clk, reset = 1, reset_slave = 1;

wire mosi, sclk, cs, tx_d, rx_d, miso, slave_d, slave_tx_d;

reg [7:0] data = 8'b10110111, data_slave = 8'b10101101;
wire [7:0] rx_data, rx_master_data;

spi_master u1(
    .clk(clk),
    .reset(reset),
    .spi_clk(sclk),
    .mosi(mosi),
    .miso(miso),
    .cs(cs),
    .tx_done(tx_d),
    .rx_done(rx_d),
    .tx_data(data),
    .rx_data(rx_master_data)
);

spi_slave u2(
    .clk(clk),
    .reset(reset_slave),
    .spi_clk(sclk),
    .mosi(mosi),
    .miso(miso),
    .cs(cs),
    .rx_data(rx_data),
    .rx_done(slave_d),
    .tx_done(slave_tx_d),
    .tx_data(data_slave)
);

initial begin
    clk = 0;
    $dumpfile("spi.vcd");
    $dumpvars;

    $display("RX data %d", rx_data);
    $display("TX slave data %b", data_slave);

    #1
    reset = 0;
    reset_slave = 0;

    #2
    reset = 1;
    reset_slave = 1;

    #5500 // a formula e div_clk * 40 

    $display("TX Done %b", slave_tx_d);
    $display("RX Done %b", slave_d);
    $display("RX data %b", rx_data);
    $display("RX data master %b", rx_master_data);

    $display("");

    $display("Segundo round");

    data = 8'b11111011;
    data_slave = 8'b10001001;

    $display("TX master %b", data);
    $display("TX slave data %b", data_slave);

    $display("");

    $display("RX master %b", rx_master_data);
    $display("RX slave data %b", rx_data);

    $display("");

    #2

    //reset_slave = 0;
    reset = 0;

    #2

    reset = 1;
    //reset_slave = 1;

    #5500 // a formula e div_clk * 40 

    $display("TX master %b", data);
    $display("TX slave data %b", data_slave);

    $display("");

    $display("RX master %b", rx_master_data);
    $display("RX slave data %b", rx_data);

    $finish;

end

endmodule

spi/spi.vcd
$date
	Mon Oct 30 22:31:43 2023
$end
$version
	Icarus Verilog
$end
$timescale
	1s
$end
$scope module test $end
$var wire 1 ! tx_d $end
$var wire 1 " slave_tx_d $end
$var wire 1 # slave_d $end
$var wire 1 $ sclk $end
$var wire 8 % rx_master_data [7:0] $end
$var wire 8 & rx_data [7:0] $end
$var wire 1 ' rx_d $end
$var wire 1 ( mosi $end
$var wire 1 ) miso $end
$var wire 1 * cs $end
$var reg 1 + clk $end
$var reg 8 , data [7:0] $end
$var reg 8 - data_slave [7:0] $end
$var reg 1 . reset $end
$var reg 1 / reset_slave $end
$scope module u1 $end
$var wire 1 + clk $end
$var wire 1 * cs $end
$var wire 1 ( mosi $end
$var wire 1 . reset $end
$var wire 8 0 rx_data [7:0] $end
$var wire 1 ' rx_done $end
$var wire 1 $ spi_clk $end
$var wire 8 1 tx_data [7:0] $end
$var wire 1 ! tx_done $end
$var wire 1 ) miso $end
$var parameter 32 2 CLK_DIV $end
$var parameter 32 3 START $end
$var parameter 32 4 STOP $end
$var parameter 32 5 WORK $end
$var reg 10 6 clk_counter [9:0] $end
$var reg 1 7 clk_r $end
$var reg 4 8 cont [3:0] $end
$var reg 4 9 cont_rx [3:0] $end
$var reg 1 : cs_r $end
$var reg 1 ; mosi_r $end
$var reg 8 < rx_data_r [7:0] $end
$var reg 1 = rx_done_r $end
$var reg 2 > state [1:0] $end
$var reg 1 ? trig $end
$var reg 8 @ tx_data_r [7:0] $end
$var reg 1 A tx_done_r $end
$upscope $end
$scope module u2 $end
$var wire 1 + clk $end
$var wire 1 * cs $end
$var wire 1 ) miso $end
$var wire 1 ( mosi $end
$var wire 1 / reset $end
$var wire 8 B rx_data [7:0] $end
$var wire 1 # rx_done $end
$var wire 1 $ spi_clk $end
$var wire 8 C tx_data [7:0] $end
$var wire 1 " tx_done $end
$var reg 1 D autoreset $end
$var reg 4 E cont [3:0] $end
$var reg 4 F cont_sclk [3:0] $end
$var reg 4 G cont_tx [3:0] $end
$var reg 1 H miso_r $end
$var reg 8 I rx_data_r [7:0] $end
$var reg 1 J rx_done_r $end
$var reg 8 K tx_data_r [7:0] $end
$var reg 1 L tx_done_r $end
$upscope $end
$upscope $end
$enddefinitions $end
$comment Show the parameter values. $end
$dumpall
b1 5
b10 4
b0 3
b100001110 2
$end
#0
$dumpvars
1L
b0 K
1J
b0 I
0H
b0 G
b0 F
b0 E
0D
b10101101 C
b0 B
1A
bx @
x?
b10 >
1=
bx <
0;
1:
b0 9
b0 8
07
b0 6
b10110111 1
bx 0
1/
1.
b10101101 -
b10110111 ,
0+
1*
0)
0(
1'
b0 &
bx %
0$
1#
1"
1!
$end
#1
b10110111 @
0!
0A
b0 >
0/
0.
1+
#2
0+
#3
1?
b1 >
0*
0:
1+
1/
1.
#4
0+
#5
b1 6
b1 8
1(
1;
b1101110 @
1)
1H
0"
0L
b10101101 K
1+
#6
0+
#7
b10 6
1+
#8
0+
#9
b11 6
1+
#10
0+
#11
b100 6
1+
#12
0+
#13
b101 6
1+
#14
0+
#15
b110 6
1+
#16
0+
#17
b111 6
1+
#18
0+
#19
b1000 6
1+
#20
0+
#21
b1001 6
1+
#22
0+
#23
b1010 6
1+
#24
0+
#25
b1011 6
1+
#26
0+
#27
b1100 6
1+
#28
0+
#29
b1101 6
1+
#30
0+
#31
b1110 6
1+
#32
0+
#33
b1111 6
1+
#34
0+
#35
b10000 6
1+
#36
0+
#37
b10001 6
1+
#38
0+
#39
b10010 6
1+
#40
0+
#41
b10011 6
1+
#42
0+
#43
b10100 6
1+
#44
0+
#45
b10101 6
1+
#46
0+
#47
b10110 6
1+
#48
0+
#49
b10111 6
1+
#50
0+
#51
b11000 6
1+
#52
0+
#53
b11001 6
1+
#54
0+
#55
b11010 6
1+
#56
0+
#57
b11011 6
1+
#58
0+
#59
b11100 6
1+
#60
0+
#61
b11101 6
1+
#62
0+
#63
b11110 6
1+
#64
0+
#65
b11111 6
1+
#66
0+
#67
b100000 6
1+
#68
0+
#69
b100001 6
1+
#70
0+
#71
b100010 6
1+
#72
0+
#73
b100011 6
1+
#74
0+
#75
b100100 6
1+
#76
0+
#77
b100101 6
1+
#78
0+
#79
b100110 6
1+
#80
0+
#81
b100111 6
1+
#82
0+
#83
b101000 6
1+
#84
0+
#85
b101001 6
1+
#86
0+
#87
b101010 6
1+
#88
0+
#89
b101011 6
1+
#90
0+
#91
b101100 6
1+
#92
0+
#93
b101101 6
1+
#94
0+
#95
b101110 6
1+
#96
0+
#97
b101111 6
1+
#98
0+
#99
b110000 6
1+
#100
0+
#101
b110001 6
1+
#102
0+
#103
b110010 6
1+
#104
0+
#105
b110011 6
1+
#106
0+
#107
b110100 6
1+
#108
0+
#109
b110101 6
1+
#110
0+
#111
b110110 6
1+
#112
0+
#113
b110111 6
1+
#114
0+
#115
b111000 6
1+
#116
0+
#117
b111001 6
1+
#118
0+
#119
b111010 6
1+
#120
0+
#121
b111011 6
1+
#122
0+
#123
b111100 6
1+
#124
0+
#125
b111101 6
1+
#126
0+
#127
b111110 6
1+
#128
0+
#129
b111111 6
1+
#130
0+
#131
b1000000 6
1+
#132
0+
#133
b1000001 6
1+
#134
0+
#135
b1000010 6
1+
#136
0+
#137
b1000011 6
1+
#138
0+
#139
b1000100 6
1+
#140
0+
#141
b1000101 6
1+
#142
0+
#143
b1000110 6
1+
#144
0+
#145
b1000111 6
1+
#146
0+
#147
b1001000 6
1+
#148
0+
#149
b1001001 6
1+
#150
0+
#151
b1001010 6
1+
#152
0+
#153
b1001011 6
1+
#154
0+
#155
b1001100 6
1+
#156
0+
#157
b1001101 6
1+
#158
0+
#159
b1001110 6
1+
#160
0+
#161
b1001111 6
1+
#162
0+
#163
b1010000 6
1+
#164
0+
#165
b1010001 6
1+
#166
0+
#167
b1010010 6
1+
#168
0+
#169
b1010011 6
1+
#170
0+
#171
b1010100 6
1+
#172
0+
#173
b1010101 6
1+
#174
0+
#175
b1010110 6
1+
#176
0+
#177
b1010111 6
1+
#178
0+
#179
b1011000 6
1+
#180
0+
#181
b1011001 6
1+
#182
0+
#183
b1011010 6
1+
#184
0+
#185
b1011011 6
1+
#186
0+
#187
b1011100 6
1+
#188
0+
#189
b1011101 6
1+
#190
0+
#191
b1011110 6
1+
#192
0+
#193
b1011111 6
1+
#194
0+
#195
b1100000 6
1+
#196
0+
#197
b1100001 6
1+
#198
0+
#199
b1100010 6
1+
#200
0+
#201
b1100011 6
1+
#202
0+
#203
b1100100 6
1+
#204
0+
#205
b1100101 6
1+
#206
0+
#207
b1100110 6
1+
#208
0+
#209
b1100111 6
1+
#210
0+
#211
b1101000 6
1+
#212
0+
#213
b1101001 6
1+
#214
0+
#215
b1101010 6
1+
#216
0+
#217
b1101011 6
1+
#218
0+
#219
b1101100 6
1+
#220
0+
#221
b1101101 6
1+
#222
0+
#223
b1101110 6
1+
#224
0+
#225
b1101111 6
1+
#226
0+
#227
b1110000 6
1+
#228
0+
#229
b1110001 6
1+
#230
0+
#231
b1110010 6
1+
#232
0+
#233
b1110011 6
1+
#234
0+
#235
b1110100 6
1+
#236
0+
#237
b1110101 6
1+
#238
0+
#239
b1110110 6
1+
#240
0+
#241
b1110111 6
1+
#242
0+
#243
b1111000 6
1+
#244
0+
#245
b1111001 6
1+
#246
0+
#247
b1111010 6
1+
#248
0+
#249
b1111011 6
1+
#250
0+
#251
b1111100 6
1+
#252
0+
#253
b1111101 6
1+
#254
0+
#255
b1111110 6
1+
#256
0+
#257
b1111111 6
1+
#258
0+
#259
b10000000 6
1+
#260
0+
#261
b10000001 6
1+
#262
0+
#263
b10000010 6
1+
#264
0+
#265
b10000011 6
1+
#266
0+
#267
b10000100 6
1+
#268
0+
#269
b10000101 6
1+
#270
0+
#271
b10000110 6
1+
#272
0+
#273
b10000111 6
1+
#274
0+
#275
b1 9
bx1 %
bx1 0
bx1 <
0'
0=
b1 E
b1 &
b1 B
b1 I
0#
0J
b10001000 6
1$
17
1+
#276
0+
#277
b10001001 6
1+
#278
0+
#279
b10001010 6
1+
#280
0+
#281
b10001011 6
1+
#282
0+
#283
b10001100 6
1+
#284
0+
#285
b10001101 6
1+
#286
0+
#287
b10001110 6
1+
#288
0+
#289
b10001111 6
1+
#290
0+
#291
b10010000 6
1+
#292
0+
#293
b10010001 6
1+
#294
0+
#295
b10010010 6
1+
#296
0+
#297
b10010011 6
1+
#298
0+
#299
b10010100 6
1+
#300
0+
#301
b10010101 6
1+
#302
0+
#303
b10010110 6
1+
#304
0+
#305
b10010111 6
1+
#306
0+
#307
b10011000 6
1+
#308
0+
#309
b10011001 6
1+
#310
0+
#311
b10011010 6
1+
#312
0+
#313
b10011011 6
1+
#314
0+
#315
b10011100 6
1+
#316
0+
#317
b10011101 6
1+
#318
0+
#319
b10011110 6
1+
#320
0+
#321
b10011111 6
1+
#322
0+
#323
b10100000 6
1+
#324
0+
#325
b10100001 6
1+
#326
0+
#327
b10100010 6
1+
#328
0+
#329
b10100011 6
1+
#330
0+
#331
b10100100 6
1+
#332
0+
#333
b10100101 6
1+
#334
0+
#335
b10100110 6
1+
#336
0+
#337
b10100111 6
1+
#338
0+
#339
b10101000 6
1+
#340
0+
#341
b10101001 6
1+
#342
0+
#343
b10101010 6
1+
#344
0+
#345
b10101011 6
1+
#346
0+
#347
b10101100 6
1+
#348
0+
#349
b10101101 6
1+
#350
0+
#351
b10101110 6
1+
#352
0+
#353
b10101111 6
1+
#354
0+
#355
b10110000 6
1+
#356
0+
#357
b10110001 6
1+
#358
0+
#359
b10110010 6
1+
#360
0+
#361
b10110011 6
1+
#362
0+
#363
b10110100 6
1+
#364
0+
#365
b10110101 6
1+
#366
0+
#367
b10110110 6
1+
#368
0+
#369
b10110111 6
1+
#370
0+
#371
b10111000 6
1+
#372
0+
#373
b10111001 6
1+
#374
0+
#375
b10111010 6
1+
#376
0+
#377
b10111011 6
1+
#378
0+
#379
b10111100 6
1+
#380
0+
#381
b10111101 6
1+
#382
0+
#383
b10111110 6
1+
#384
0+
#385
b10111111 6
1+
#386
0+
#387
b11000000 6
1+
#388
0+
#389
b11000001 6
1+
#390
0+
#391
b11000010 6
1+
#392
0+
#393
b11000011 6
1+
#394
0+
#395
b11000100 6
1+
#396
0+
#397
b11000101 6
1+
#398
0+
#399
b11000110 6
1+
#400
0+
#401
b11000111 6
1+
#402
0+
#403
b11001000 6
1+
#404
0+
#405
b11001001 6
1+
#406
0+
#407
b11001010 6
1+
#408
0+
#409
b11001011 6
1+
#410
0+
#411
b11001100 6
1+
#412
0+
#413
b11001101 6
1+
#414
0+
#415
b11001110 6
1+
#416
0+
#417
b11001111 6
1+
#418
0+
#419
b11010000 6
1+
#420
0+
#421
b11010001 6
1+
#422
0+
#423
b11010010 6
1+
#424
0+
#425
b11010011 6
1+
#426
0+
#427
b11010100 6
1+
#428
0+
#429
b11010101 6
1+
#430
0+
#431
b11010110 6
1+
#432
0+
#433
b11010111 6
1+
#434
0+
#435
b11011000 6
1+
#436
0+
#437
b11011001 6
1+
#438
0+
#439
b11011010 6
1+
#440
0+
#441
b11011011 6
1+
#442
0+
#443
b11011100 6
1+
#444
0+
#445
b11011101 6
1+
#446
0+
#447
b11011110 6
1+
#448
0+
#449
b11011111 6
1+
#450
0+
#451
b11100000 6
1+
#452
0+
#453
b11100001 6
1+
#454
0+
#455
b11100010 6
1+
#456
0+
#457
b11100011 6
1+
#458
0+
#459
b11100100 6
1+
#460
0+
#461
b11100101 6
1+
#462
0+
#463
b11100110 6
1+
#464
0+
#465
b11100111 6
1+
#466
0+
#467
b11101000 6
1+
#468
0+
#469
b11101001 6
1+
#470
0+
#471
b11101010 6
1+
#472
0+
#473
b11101011 6
1+
#474
0+
#475
b11101100 6
1+
#476
0+
#477
b11101101 6
1+
#478
0+
#479
b11101110 6
1+
#480
0+
#481
b11101111 6
1+
#482
0+
#483
b11110000 6
1+
#484
0+
#485
b11110001 6
1+
#486
0+
#487
b11110010 6
1+
#488
0+
#489
b11110011 6
1+
#490
0+
#491
b11110100 6
1+
#492
0+
#493
b11110101 6
1+
#494
0+
#495
b11110110 6
1+
#496
0+
#497
b11110111 6
1+
#498
0+
#499
b11111000 6
1+
#500
0+
#501
b11111001 6
1+
#502
0+
#503
b11111010 6
1+
#504
0+
#505
b11111011 6
1+
#506
0+
#507
b11111100 6
1+
#508
0+
#509
b11111101 6
1+
#510
0+
#511
b11111110 6
1+
#512
0+
#513
b11111111 6
1+
#514
0+
#515
b100000000 6
1+
#516
0+
#517
b100000001 6
1+
#518
0+
#519
b100000010 6
1+
#520
0+
#521
b100000011 6
1+
#522
0+
#523
b100000100 6
1+
#524
0+
#525
b100000101 6
1+
#526
0+
#527
b100000110 6
1+
#528
0+
#529
b100000111 6
1+
#530
0+
#531
b100001000 6
1+
#532
0+
#533
b100001001 6
1+
#534
0+
#535
b100001010 6
1+
#536
0+
#537
b100001011 6
1+
#538
0+
#539
b100001100 6
1+
#540
0+
#541
b100001101 6
1+
#542
0+
#543
b0 6
1+
#544
0+
#545
b1 F
b1 6
0$
07
b10 8
0(
0;
b11011100 @
1+
#546
0+
#547
b1 G
b1011010 K
b10 6
1+
#548
0+
#549
b11 6
0)
0H
1+
#550
0+
#551
b100 6
1+
#552
0+
#553
b101 6
1+
#554
0+
#555
b110 6
1+
#556
0+
#557
b111 6
1+
#558
0+
#559
b1000 6
1+
#560
0+
#561
b1001 6
1+
#562
0+
#563
b1010 6
1+
#564
0+
#565
b1011 6
1+
#566
0+
#567
b1100 6
1+
#568
0+
#569
b1101 6
1+
#570
0+
#571
b1110 6
1+
#572
0+
#573
b1111 6
1+
#574
0+
#575
b10000 6
1+
#576
0+
#577
b10001 6
1+
#578
0+
#579
b10010 6
1+
#580
0+
#581
b10011 6
1+
#582
0+
#583
b10100 6
1+
#584
0+
#585
b10101 6
1+
#586
0+
#587
b10110 6
1+
#588
0+
#589
b10111 6
1+
#590
0+
#591
b11000 6
1+
#592
0+
#593
b11001 6
1+
#594
0+
#595
b11010 6
1+
#596
0+
#597
b11011 6
1+
#598
0+
#599
b11100 6
1+
#600
0+
#601
b11101 6
1+
#602
0+
#603
b11110 6
1+
#604
0+
#605
b11111 6
1+
#606
0+
#607
b100000 6
1+
#608
0+
#609
b100001 6
1+
#610
0+
#611
b100010 6
1+
#612
0+
#613
b100011 6
1+
#614
0+
#615
b100100 6
1+
#616
0+
#617
b100101 6
1+
#618
0+
#619
b100110 6
1+
#620
0+
#621
b100111 6
1+
#622
0+
#623
b101000 6
1+
#624
0+
#625
b101001 6
1+
#626
0+
#627
b101010 6
1+
#628
0+
#629
b101011 6
1+
#630
0+
#631
b101100 6
1+
#632
0+
#633
b101101 6
1+
#634
0+
#635
b101110 6
1+
#636
0+
#637
b101111 6
1+
#638
0+
#639
b110000 6
1+
#640
0+
#641
b110001 6
1+
#642
0+
#643
b110010 6
1+
#644
0+
#645
b110011 6
1+
#646
0+
#647
b110100 6
1+
#648
0+
#649
b110101 6
1+
#650
0+
#651
b110110 6
1+
#652
0+
#653
b110111 6
1+
#654
0+
#655
b111000 6
1+
#656
0+
#657
b111001 6
1+
#658
0+
#659
b111010 6
1+
#660
0+
#661
b111011 6
1+
#662
0+
#663
b111100 6
1+
#664
0+
#665
b111101 6
1+
#666
0+
#667
b111110 6
1+
#668
0+
#669
b111111 6
1+
#670
0+
#671
b1000000 6
1+
#672
0+
#673
b1000001 6
1+
#674
0+
#675
b1000010 6
1+
#676
0+
#677
b1000011 6
1+
#678
0+
#679
b1000100 6
1+
#680
0+
#681
b1000101 6
1+
#682
0+
#683
b1000110 6
1+
#684
0+
#685
b1000111 6
1+
#686
0+
#687
b1001000 6
1+
#688
0+
#689
b1001001 6
1+
#690
0+
#691
b1001010 6
1+
#692
0+
#693
b1001011 6
1+
#694
0+
#695
b1001100 6
1+
#696
0+
#697
b1001101 6
1+
#698
0+
#699
b1001110 6
1+
#700
0+
#701
b1001111 6
1+
#702
0+
#703
b1010000 6
1+
#704
0+
#705
b1010001 6
1+
#706
0+
#707
b1010010 6
1+
#708
0+
#709
b1010011 6
1+
#710
0+
#711
b1010100 6
1+
#712
0+
#713
b1010101 6
1+
#714
0+
#715
b1010110 6
1+
#716
0+
#717
b1010111 6
1+
#718
0+
#719
b1011000 6
1+
#720
0+
#721
b1011001 6
1+
#722
0+
#723
b1011010 6
1+
#724
0+
#725
b1011011 6
1+
#726
0+
#727
b1011100 6
1+
#728
0+
#729
b1011101 6
1+
#730
0+
#731
b1011110 6
1+
#732
0+
#733
b1011111 6
1+
#734
0+
#735
b1100000 6
1+
#736
0+
#737
b1100001 6
1+
#738
0+
#739
b1100010 6
1+
#740
0+
#741
b1100011 6
1+
#742
0+
#743
b1100100 6
1+
#744
0+
#745
b1100101 6
1+
#746
0+
#747
b1100110 6
1+
#748
0+
#749
b1100111 6
1+
#750
0+
#751
b1101000 6
1+
#752
0+
#753
b1101001 6
1+
#754
0+
#755
b1101010 6
1+
#756
0+
#757
b1101011 6
1+
#758
0+
#759
b1101100 6
1+
#760
0+
#761
b1101101 6
1+
#762
0+
#763
b1101110 6
1+
#764
0+
#765
b1101111 6
1+
#766
0+
#767
b1110000 6
1+
#768
0+
#769
b1110001 6
1+
#770
0+
#771
b1110010 6
1+
#772
0+
#773
b1110011 6
1+
#774
0+
#775
b1110100 6
1+
#776
0+
#777
b1110101 6
1+
#778
0+
#779
b1110110 6
1+
#780
0+
#781
b1110111 6
1+
#782
0+
#783
b1111000 6
1+
#784
0+
#785
b1111001 6
1+
#786
0+
#787
b1111010 6
1+
#788
0+
#789
b1111011 6
1+
#790
0+
#791
b1111100 6
1+
#792
0+
#793
b1111101 6
1+
#794
0+
#795
b1111110 6
1+
#796
0+
#797
b1111111 6
1+
#798
0+
#799
b10000000 6
1+
#800
0+
#801
b10000001 6
1+
#802
0+
#803
b10000010 6
1+
#804
0+
#805
b10000011 6
1+
#806
0+
#807
b10000100 6
1+
#808
0+
#809
b10000101 6
1+
#810
0+
#811
b10000110 6
1+
#812
0+
#813
b10000111 6
1+
#814
0+
#815
b10 E
b10 &
b10 B
b10 I
b10 9
bx10 %
bx10 0
bx10 <
b10001000 6
1$
17
1+
#816
0+
#817
b10001001 6
1+
#818
0+
#819
b10001010 6
1+
#820
0+
#821
b10001011 6
1+
#822
0+
#823
b10001100 6
1+
#824
0+
#825
b10001101 6
1+
#826
0+
#827
b10001110 6
1+
#828
0+
#829
b10001111 6
1+
#830
0+
#831
b10010000 6
1+
#832
0+
#833
b10010001 6
1+
#834
0+
#835
b10010010 6
1+
#836
0+
#837
b10010011 6
1+
#838
0+
#839
b10010100 6
1+
#840
0+
#841
b10010101 6
1+
#842
0+
#843
b10010110 6
1+
#844
0+
#845
b10010111 6
1+
#846
0+
#847
b10011000 6
1+
#848
0+
#849
b10011001 6
1+
#850
0+
#851
b10011010 6
1+
#852
0+
#853
b10011011 6
1+
#854
0+
#855
b10011100 6
1+
#856
0+
#857
b10011101 6
1+
#858
0+
#859
b10011110 6
1+
#860
0+
#861
b10011111 6
1+
#862
0+
#863
b10100000 6
1+
#864
0+
#865
b10100001 6
1+
#866
0+
#867
b10100010 6
1+
#868
0+
#869
b10100011 6
1+
#870
0+
#871
b10100100 6
1+
#872
0+
#873
b10100101 6
1+
#874
0+
#875
b10100110 6
1+
#876
0+
#877
b10100111 6
1+
#878
0+
#879
b10101000 6
1+
#880
0+
#881
b10101001 6
1+
#882
0+
#883
b10101010 6
1+
#884
0+
#885
b10101011 6
1+
#886
0+
#887
b10101100 6
1+
#888
0+
#889
b10101101 6
1+
#890
0+
#891
b10101110 6
1+
#892
0+
#893
b10101111 6
1+
#894
0+
#895
b10110000 6
1+
#896
0+
#897
b10110001 6
1+
#898
0+
#899
b10110010 6
1+
#900
0+
#901
b10110011 6
1+
#902
0+
#903
b10110100 6
1+
#904
0+
#905
b10110101 6
1+
#906
0+
#907
b10110110 6
1+
#908
0+
#909
b10110111 6
1+
#910
0+
#911
b10111000 6
1+
#912
0+
#913
b10111001 6
1+
#914
0+
#915
b10111010 6
1+
#916
0+
#917
b10111011 6
1+
#918
0+
#919
b10111100 6
1+
#920
0+
#921
b10111101 6
1+
#922
0+
#923
b10111110 6
1+
#924
0+
#925
b10111111 6
1+
#926
0+
#927
b11000000 6
1+
#928
0+
#929
b11000001 6
1+
#930
0+
#931
b11000010 6
1+
#932
0+
#933
b11000011 6
1+
#934
0+
#935
b11000100 6
1+
#936
0+
#937
b11000101 6
1+
#938
0+
#939
b11000110 6
1+
#940
0+
#941
b11000111 6
1+
#942
0+
#943
b11001000 6
1+
#944
0+
#945
b11001001 6
1+
#946
0+
#947
b11001010 6
1+
#948
0+
#949
b11001011 6
1+
#950
0+
#951
b11001100 6
1+
#952
0+
#953
b11001101 6
1+
#954
0+
#955
b11001110 6
1+
#956
0+
#957
b11001111 6
1+
#958
0+
#959
b11010000 6
1+
#960
0+
#961
b11010001 6
1+
#962
0+
#963
b11010010 6
1+
#964
0+
#965
b11010011 6
1+
#966
0+
#967
b11010100 6
1+
#968
0+
#969
b11010101 6
1+
#970
0+
#971
b11010110 6
1+
#972
0+
#973
b11010111 6
1+
#974
0+
#975
b11011000 6
1+
#976
0+
#977
b11011001 6
1+
#978
0+
#979
b11011010 6
1+
#980
0+
#981
b11011011 6
1+
#982
0+
#983
b11011100 6
1+
#984
0+
#985
b11011101 6
1+
#986
0+
#987
b11011110 6
1+
#988
0+
#989
b11011111 6
1+
#990
0+
#991
b11100000 6
1+
#992
0+
#993
b11100001 6
1+
#994
0+
#995
b11100010 6
1+
#996
0+
#997
b11100011 6
1+
#998
0+
#999
b11100100 6
1+
#1000
0+
#1001
b11100101 6
1+
#1002
0+
#1003
b11100110 6
1+
#1004
0+
#1005
b11100111 6
1+
#1006
0+
#1007
b11101000 6
1+
#1008
0+
#1009
b11101001 6
1+
#1010
0+
#1011
b11101010 6
1+
#1012
0+
#1013
b11101011 6
1+
#1014
0+
#1015
b11101100 6
1+
#1016
0+
#1017
b11101101 6
1+
#1018
0+
#1019
b11101110 6
1+
#1020
0+
#1021
b11101111 6
1+
#1022
0+
#1023
b11110000 6
1+
#1024
0+
#1025
b11110001 6
1+
#1026
0+
#1027
b11110010 6
1+
#1028
0+
#1029
b11110011 6
1+
#1030
0+
#1031
b11110100 6
1+
#1032
0+
#1033
b11110101 6
1+
#1034
0+
#1035
b11110110 6
1+
#1036
0+
#1037
b11110111 6
1+
#1038
0+
#1039
b11111000 6
1+
#1040
0+
#1041
b11111001 6
1+
#1042
0+
#1043
b11111010 6
1+
#1044
0+
#1045
b11111011 6
1+
#1046
0+
#1047
b11111100 6
1+
#1048
0+
#1049
b11111101 6
1+
#1050
0+
#1051
b11111110 6
1+
#1052
0+
#1053
b11111111 6
1+
#1054
0+
#1055
b100000000 6
1+
#1056
0+
#1057
b100000001 6
1+
#1058
0+
#1059
b100000010 6
1+
#1060
0+
#1061
b100000011 6
1+
#1062
0+
#1063
b100000100 6
1+
#1064
0+
#1065
b100000101 6
1+
#1066
0+
#1067
b100000110 6
1+
#1068
0+
#1069
b100000111 6
1+
#1070
0+
#1071
b100001000 6
1+
#1072
0+
