spi/src/spi_slave.v
module spi_slave (
    input clk,
    input reset,
    output [7:0] rx_data,
    input [7:0] tx_data,

    //spi
    input spi_clk,
    output miso,
    input mosi,
    input cs,
    output rx_done,
    output tx_done
);

reg[3:0] cont, cont_tx;
reg [7:0]rx_data_r, tx_data_r;
reg rx_done_r, tx_done_r, miso_r;

assign rx_done = rx_done_r;
assign tx_done = tx_done_r;
assign miso = miso_r;

initial begin
    cont = 0;
    rx_data_r = 8'b0;
    rx_done_r = 1'b1;
    tx_done_r = 1'b1;
    miso_r = 0;
    cont_tx = 0;
    tx_data_r = 0;
end

always @(posedge spi_clk ) begin
    if(~reset) begin // isso e uma gambiarra por causa do sintetizador
        cont <= 0;
        rx_data_r <= 8'b0;
    end else if(~cs) begin
        if(cont == 0)begin
            rx_done_r <= 0;
            rx_data_r <= {mosi, rx_data_r[7:1]};
            cont <= cont + 1;
        end else if(cont < 8) begin 
            rx_data_r <= {mosi, rx_data_r[7:1]};
            cont <= cont + 1;
            if(cont == 7)
                rx_done_r <= 1;
        end else begin
            cont <= 0;
        end
    end    
end


/* o yosys suporta isso daqui, mas o gowin não, 
    ai fiz a cambiarra de verificar o reset em 2 lugares
always @(negedge reset) begin
    if(~reset) begin
        cont <= 0;
        cont_tx <= 0;
        rx_data_r <= 8'b0;
    end
end
*/
always @(posedge clk ) begin
    if(~reset) begin // isso e uma gambiarra por causa do sintetizador
        cont_tx <= 0;
        miso_r <= 0;
    end else if(~cs) begin
        if(cont_tx == 0)begin
            tx_data_r = tx_data;
            tx_done_r <= 0;
            miso_r <= tx_data_r[7];
            tx_data_r <= {tx_data_r[6:0], 1'b0};
            //miso_r <= 1;
            cont_tx <= cont_tx + 1;
        end else if(cont_tx < 8) begin 
            tx_data_r <= {tx_data_r[6:0], 1'b0};
            miso_r <= tx_data_r[7];
            //miso_r <= 1;
            cont_tx <= cont_tx + 1;
            if(cont_tx == 7) begin
                tx_done_r <= 1;
                cont_tx <= 0;
                miso_r <= 0;
            end 
        end else begin
            cont_tx <= 0;
            miso_r <= 0;
        end
    end   
end

assign rx_data = rx_data_r;
    
endmodule
// pra implementar divisão de clock, precisa organizar envio de acordo com spiclk

spi/src/spi_master.v
module spi_master (
    input clk,
    input reset,
    output spi_clk, // clk da spi
    output mosi, // master output slave input
    input miso, // master input slave output
    output cs, // chip select
    input [7:0] tx_data, 
    output [7:0] rx_data,
    output tx_done,  // Sinal indicando que a transmissão está concluída
    output rx_done
);

parameter START = 0, WORK = 1, STOP = 2;
reg [1:0] state = STOP; // estados da maquina

reg mosi_r, cs_r, tx_done_r, rx_done_r, clk_r;

//assign spi_clk = clk_r;
assign spi_clk = ~clk;
reg [3:0] cont = 0, cont_rx = 0;
reg [7:0] tx_data_r, rx_data_r;

assign mosi = mosi_r;
assign cs = cs_r;
assign tx_done = tx_done_r;
assign rx_data = rx_data_r;
assign rx_done = rx_done_r;

initial begin
    cs_r = 1;
    tx_done_r = 1;
    rx_done_r = 1;
    mosi_r = 0;
    clk_r = 1;
end

always @(posedge clk) begin
    if (~reset) begin
        state <= START;
        mosi_r <= 1'b0;
        tx_done_r <= 1'b0;
        cs_r <= 1'b1;
        tx_data_r <= tx_data;
    end else begin
        case (state)
            START: begin
                tx_done_r <= 1'b0;
                cs_r <= 1'b0;
                mosi_r <= tx_data_r[7];
                tx_data_r <= {tx_data_r[6:0], 1'b0};
                state <= WORK;
                cont <= 0;
            end
            WORK: begin
                if(cont == 6)
                    state <= STOP;
                tx_data_r <= {tx_data_r[6:0], 1'b0};
                mosi_r <= tx_data_r[7];
                cont <= cont + 1;
            end
            STOP: begin
                tx_done_r <= 1'b1;
                state <= STOP;
                mosi_r <= 1'b0;
                cs_r <= 1'b1;
            end
            default: begin
                state <= STOP;
            end
        endcase // case
    end // reset
end // always

always @(posedge spi_clk ) begin
    if (~reset) begin
        cont_rx <= 0;
    end else if(~cs) begin
        if(cont_rx == 0)begin
            rx_done_r <= 0;
            rx_data_r <= {miso, rx_data_r[7:1]};
            cont_rx <= cont_rx + 1;
        end else if(cont_rx < 8) begin 
            rx_data_r <= {miso, rx_data_r[7:1]};
            cont_rx <= cont_rx + 1;
            if(cont_rx == 7)
                rx_done_r <= 1;
        end else begin
            cont_rx <= 0;
        end
    end   // cs
end // always
    
endmodule

spi/src/spi_test.v
module test();

always #1 clk=~clk;

reg clk, reset = 1, reset_slave = 1;

wire mosi, sclk, cs, tx_d, rx_d, miso, slave_d, slave_tx_d;

reg [7:0] data = 8'b10110101, data_slave = 8'b10101101;
wire [7:0] rx_data, rx_master_data;

spi_master u1(
    .clk(clk),
    .reset(reset),
    .spi_clk(sclk),
    .mosi(mosi),
    .miso(miso),
    .cs(cs),
    .tx_done(tx_d),
    .rx_done(rx_d),
    .tx_data(data),
    .rx_data(rx_master_data)
);

spi_slave u2(
    .clk(clk),
    .reset(reset_slave),
    .spi_clk(sclk),
    .mosi(mosi),
    .miso(miso),
    .cs(cs),
    .rx_data(rx_data),
    .rx_done(slave_d),
    .tx_done(slave_tx_d),
    .tx_data(data_slave)
);

initial begin
    clk = 0;
    $dumpfile("spi.vcd");
    $dumpvars;

    $display("RX data %d", rx_data);
    $display("TX slave data %b", data_slave);

    #1
    reset = 0;
    reset_slave = 0;

    #2
    reset = 1;
    reset_slave = 1;

    #20

    $display("TX Done %b", slave_tx_d);
    $display("RX Done %b", slave_d);
    $display("RX data %b", rx_data);
    $display("RX data master %b", rx_master_data);

    $finish;

end

endmodule

spi/spi.vcd
$date
	Tue Oct 24 00:20:18 2023
$end
$version
	Icarus Verilog
$end
$timescale
	1s
$end
$scope module test $end
$var wire 1 ! tx_d $end
$var wire 1 " slave_tx_d $end
$var wire 1 # slave_d $end
$var wire 1 $ sclk $end
$var wire 8 % rx_master_data [7:0] $end
$var wire 8 & rx_data [7:0] $end
$var wire 1 ' rx_d $end
$var wire 1 ( mosi $end
$var wire 1 ) miso $end
$var wire 1 * cs $end
$var reg 1 + clk $end
$var reg 8 , data [7:0] $end
$var reg 8 - data_slave [7:0] $end
$var reg 1 . reset $end
$var reg 1 / reset_slave $end
$scope module u1 $end
$var wire 1 + clk $end
$var wire 1 * cs $end
$var wire 1 ( mosi $end
$var wire 1 . reset $end
$var wire 8 0 rx_data [7:0] $end
$var wire 1 ' rx_done $end
$var wire 1 $ spi_clk $end
$var wire 8 1 tx_data [7:0] $end
$var wire 1 ! tx_done $end
$var wire 1 ) miso $end
$var parameter 32 2 START $end
$var parameter 32 3 STOP $end
$var parameter 32 4 WORK $end
$var reg 1 5 clk_r $end
$var reg 4 6 cont [3:0] $end
$var reg 4 7 cont_rx [3:0] $end
$var reg 1 8 cs_r $end
$var reg 1 9 mosi_r $end
$var reg 8 : rx_data_r [7:0] $end
$var reg 1 ; rx_done_r $end
$var reg 2 < state [1:0] $end
$var reg 8 = tx_data_r [7:0] $end
$var reg 1 > tx_done_r $end
$upscope $end
$scope module u2 $end
$var wire 1 + clk $end
$var wire 1 * cs $end
$var wire 1 ) miso $end
$var wire 1 ( mosi $end
$var wire 1 / reset $end
$var wire 8 ? rx_data [7:0] $end
$var wire 1 # rx_done $end
$var wire 1 $ spi_clk $end
$var wire 8 @ tx_data [7:0] $end
$var wire 1 " tx_done $end
$var reg 4 A cont [3:0] $end
$var reg 4 B cont_tx [3:0] $end
$var reg 1 C miso_r $end
$var reg 8 D rx_data_r [7:0] $end
$var reg 1 E rx_done_r $end
$var reg 8 F tx_data_r [7:0] $end
$var reg 1 G tx_done_r $end
$upscope $end
$upscope $end
$enddefinitions $end
$comment Show the parameter values. $end
$dumpall
b1 4
b10 3
b0 2
$end
#0
$dumpvars
1G
b0 F
1E
b0 D
0C
b0 B
b0 A
b10101101 @
b0 ?
1>
bx =
b10 <
1;
bx :
09
18
b0 7
b0 6
15
b10110101 1
bx 0
1/
1.
b10101101 -
b10110101 ,
0+
1*
0)
0(
1'
b0 &
bx %
1$
1#
1"
1!
$end
#1
b10110101 =
0!
0>
b0 <
0$
0/
0.
1+
#2
1$
0+
#3
b1 <
b1101010 =
1(
19
0*
08
0$
1+
1/
1.
#4
b1 7
b0xxxxxxx %
b0xxxxxxx 0
b0xxxxxxx :
0'
0;
b1 A
b10000000 &
b10000000 ?
b10000000 D
0#
0E
1$
0+
#5
b1 6
0(
09
b11010100 =
b1 B
1)
1C
0"
0G
0$
b1011010 F
1+
#6
b10 A
b1000000 &
b1000000 ?
b1000000 D
b10 7
b10xxxxxx %
b10xxxxxx 0
b10xxxxxx :
1$
0+
#7
b10 B
0)
0C
b10110100 F
b10 6
1(
19
b10101000 =
0$
1+
#8
b11 7
b10xxxxx %
b10xxxxx 0
b10xxxxx :
b11 A
b10100000 &
b10100000 ?
b10100000 D
1$
0+
#9
b11 6
b1010000 =
b11 B
1)
1C
b1101000 F
0$
1+
#10
b100 A
b11010000 &
b11010000 ?
b11010000 D
b100 7
b1010xxxx %
b1010xxxx 0
b1010xxxx :
1$
0+
#11
b100 B
0)
0C
b11010000 F
b100 6
0(
09
b10100000 =
0$
1+
#12
b101 7
b1010xxx %
b1010xxx 0
b1010xxx :
b101 A
b1101000 &
b1101000 ?
b1101000 D
1$
0+
#13
b101 6
1(
19
b1000000 =
b101 B
1)
1C
b10100000 F
0$
1+
#14
b110 A
b10110100 &
b10110100 ?
b10110100 D
b110 7
b101010xx %
b101010xx 0
b101010xx :
1$
0+
#15
b110 B
b1000000 F
b110 6
0(
09
b10000000 =
0$
1+
#16
b111 7
b1101010x %
b1101010x 0
b1101010x :
b111 A
b1011010 &
b1011010 ?
b1011010 D
1$
0+
#17
b111 6
1(
19
b0 =
b10 <
b111 B
0)
0C
b10000000 F
0$
1+
#18
1#
1E
b1000 A
b10101101 &
b10101101 ?
b10101101 D
1'
1;
b1000 7
b1101010 %
b1101010 0
b1101010 :
1$
0+
#19
1"
1G
b0 B
0)
0C
b0 F
1*
18
0(
09
1!
1>
0$
1+
